{
  "users": [
    {
      "name": "demo",
      "email": "demo@demo",
      "password": "demo",
      "id": "1"
    },
    {
      "password": "abracadabra",
      "id": "2kic1w5yskzffqot0"
    },
    {
      "password": "abracadabra",
      "id": "2kic1wjckzfg177q"
    },
    {
      "password": "abracadabra",
      "id": "2kic1waq8kzfg5xon"
    },
    {
      "password": "abracadabra",
      "id": "2kic1w7ekkzfg9d17"
    },
    {
      "password": "abracadabra",
      "id": "2kic1w8gkkzfgbqnd"
    },
    {
      "password": "abracadabra",
      "id": "99hxkcigkzgmtclf"
    },
    {
      "password": "abracadabra",
      "id": "99hxk2c0kzgna96b"
    },
    {
      "password": "abracadabra",
      "id": "99hxk3aokzgncfeg"
    },
    {
      "password": "abracadabra",
      "id": "99hxk66gkzgnrh1x"
    },
    {
      "password": "123",
      "id": "99hxk1zwkzgo7ujo"
    },
    {
      "password": "123",
      "id": "99hxkclwkzgofz72"
    },
    {
      "password": "123",
      "id": "99hxk4h8kzgohb21"
    },
    {
      "password": "3232",
      "id": "99hxk560kzgohsng"
    },
    {
      "password": "123",
      "id": "99hxk9i8kzgoj4n7"
    },
    {
      "password": "123",
      "id": "99hxk9sgkzgokv59"
    },
    {
      "password": "123",
      "id": "99hxk3hokzgosge5"
    },
    {
      "password": "123",
      "id": "99hxk1lckzgouq8c"
    },
    {
      "password": "123",
      "id": "99hxk3cgkzgovqk3"
    },
    {
      "password": "123",
      "id": "99hxkc1ckzgowq9f"
    },
    {
      "password": "123",
      "id": "99hxk9yskzgp64kx"
    },
    {
      "password": "123",
      "id": "99hxkb7kkzgpajod"
    },
    {
      "password": "123",
      "id": "99hxk968kzgpclla"
    },
    {
      "password": "123",
      "id": "99hxkcckkzgpjnke"
    },
    {
      "password": "abracadabra",
      "id": "99hxk87skzgpo1ey"
    },
    {
      "password": "123",
      "id": "99hxk5tckzgpx3s9"
    },
    {
      "password": "123",
      "id": "99hxk21gkzgq0ita"
    },
    {
      "password": "123456789",
      "id": "99hxkc88kzgq39ci"
    },
    {
      "password": "123",
      "id": "99hxk468kzgq6y9e"
    },
    {
      "password": "123",
      "id": "99hxk9v0kzgqb43q"
    },
    {
      "password": "123",
      "id": "99hxkcegkzgqfpi6"
    },
    {
      "password": "123",
      "id": "99hxkbr4kzgqn7qe"
    },
    {
      "password": "123",
      "id": "99hxkav4kzgqogdj"
    },
    {
      "password": "123",
      "id": "99hxk7m4kzgr0zk8"
    },
    {
      "password": "123",
      "id": "99hxk6f8kzgrab28"
    },
    {
      "password": "123",
      "id": "99hxk8x8kzgrc01d"
    },
    {
      "password": "123",
      "id": "99hxkay8kzgre0em"
    },
    {
      "password": "123",
      "id": "99hxk9fwkzgrfl9b"
    },
    {
      "password": "123",
      "id": "99hxkc30kzgrpcj4"
    },
    {
      "password": "123",
      "id": "99hxk8j4kzgrqglv"
    },
    {
      "password": "123",
      "id": "99hxk904kzgrtpm0"
    },
    {
      "password": "123",
      "id": "99hxkbnckzgrubs8"
    },
    {
      "password": "123",
      "id": "99hxk5vgkzgs0svz"
    },
    {
      "password": "123",
      "id": "99hxkbf0kzgs1glu"
    },
    {
      "password": "123",
      "id": "99hxk1vkkzgs4ib5"
    },
    {
      "password": "123",
      "id": "99hxk6ugkzgs6jt6"
    },
    {
      "password": "123",
      "id": "99hxk8jkkzgsa9oc"
    },
    {
      "password": "12345",
      "id": "2kic1w44wkzgv4i7v"
    },
    {
      "password": "123",
      "id": "2kic1w6e8kzgva2qj"
    },
    {
      "password": "123",
      "id": "2kic1wblgkzgvawyb"
    },
    {
      "password": "123",
      "id": "2kic1wcmskzgvey3w"
    },
    {
      "password": "123",
      "id": "2kic1wc9gkzgvk447"
    },
    {
      "password": "123",
      "id": "2kic1w624kzgvn68i"
    },
    {
      "password": "123",
      "id": "2kic1w7aokzgvul3v"
    },
    {
      "password": "123",
      "id": "2kic1wasgkzgvx9v1"
    },
    {
      "password": "123",
      "id": "2kic1wa0okzgw53cr"
    },
    {
      "password": "1233",
      "id": "2kic1wbfwkzgw7c5x"
    },
    {
      "password": "123",
      "id": "2kic1wbg0kzgwfwgk"
    },
    {
      "password": "123",
      "id": "2kic1wab0kzgwgxjn"
    },
    {
      "password": "123",
      "id": "2kic1w4e4kzgwjq5f"
    },
    {
      "password": "123",
      "id": "2kic1w9zckzgwqvod"
    },
    {
      "password": "123",
      "id": "2kic1wbq4kzgwsn18"
    },
    {
      "password": "123",
      "id": "2kic1wc5ckzgwvdu5"
    },
    {
      "password": "123",
      "id": "2kic1w97skzgwxwgv"
    },
    {
      "password": "123",
      "id": "2kic1w2vgkzgx4z1u"
    },
    {
      "password": "123",
      "id": "2kic1w894kzgxgs7a"
    },
    {
      "password": "123",
      "id": "99hxkak8kzgyic36"
    },
    {
      "password": "123",
      "id": "99hxk3ygkzgyl7p2"
    },
    {
      "password": "123",
      "id": "99hxk8bckzgyp3dq"
    },
    {
      "password": "123",
      "id": "99hxkc3skzgyrwb7"
    },
    {
      "password": "123",
      "id": "99hxk5bkkzgz0dja"
    },
    {
      "password": "123",
      "id": "99hxk644kzgz14pq"
    },
    {
      "password": "123",
      "id": "99hxk3z8kzgz2i3z"
    },
    {
      "password": "123",
      "id": "99hxk6zwkzgz5p5r"
    },
    {
      "password": "123",
      "id": "99hxk268kzgz6aiu"
    },
    {
      "password": "123",
      "id": "99hxkbcokzgz6re6"
    },
    {
      "password": "123",
      "id": "99hxkbo4kzgz807v"
    },
    {
      "password": "123",
      "id": "99hxk74wkzgzaqvg"
    },
    {
      "password": "123",
      "id": "99hxk9dgkzgzejwn"
    },
    {
      "password": "123",
      "id": "99hxk8ggkzgzkz5i"
    },
    {
      "password": "133",
      "id": "99hxk6qskzgzqw06"
    },
    {
      "password": "123",
      "id": "99hxk6eokzgzsd3b"
    },
    {
      "password": "123",
      "id": "99hxk2bskzgzyp9c"
    },
    {
      "password": "123",
      "id": "99hxk584kzgzzhk8"
    },
    {
      "password": "123",
      "id": "99hxk5gwkzhaoz53"
    },
    {
      "password": "123",
      "id": "99hxkay8kzhb62fd"
    },
    {
      "password": "123",
      "id": "99hxk58wkzhc1zoa"
    },
    {
      "password": "123",
      "id": "99hxk5l8kzhclhwy"
    },
    {
      "password": "123",
      "id": "2kic1wb8ckzhctaix"
    },
    {
      "password": "123",
      "id": "2kic1w1mgkzhctxpm"
    },
    {
      "password": "123",
      "id": "2kic1wangkzhcwj2r"
    },
    {
      "password": "12345",
      "id": "2kic1wb8ckzhd001g"
    },
    {
      "password": "123",
      "id": "2kic1w4yckzhd3ddn"
    },
    {
      "password": "123",
      "id": "2kic1w6dckzhd5wwk"
    },
    {
      "password": "123",
      "id": "2kic1w39gkzhd922s"
    },
    {
      "password": "123",
      "id": "2kic1wa48kzhdb05m"
    },
    {
      "password": "123",
      "id": "2kic1wc2okzibi0z1"
    },
    {
      "password": "789",
      "id": "99hxk5x0kzibs1z4"
    },
    {
      "password": "1",
      "id": "99hxkal4kzibvxad"
    },
    {
      "password": "13",
      "id": "2kic1wan4kzidyahb"
    },
    {
      "password": "123",
      "id": "2kic1w7ykkzih790w"
    },
    {
      "password": "1123",
      "id": "99hxk46wkzijr2dg"
    },
    {
      "password": "123",
      "id": "99hxk818kzijtfv5"
    },
    {
      "password": "789",
      "id": "99hxk6ygkzijwt85"
    },
    {
      "password": "123456",
      "id": "99hxkbkkkzil15eq"
    },
    {
      "password": "123",
      "id": "99hxk6nskzim19wk"
    },
    {
      "password": "123",
      "id": "2kic1w2rwkzim5b56"
    },
    {
      "password": "123",
      "id": "2kic1w9g0kzim6p2s"
    },
    {
      "password": "13",
      "id": "2kic1wau4kzimlk13"
    },
    {
      "password": "123",
      "id": "2kic1w9f4kzimqtrg"
    },
    {
      "password": "789",
      "id": "2kic1w61gkzimtgh0"
    },
    {
      "password": "12345",
      "id": "2kic1w7eokzimukvw"
    },
    {
      "password": "123",
      "id": "2kic1w14okzimyput"
    },
    {
      "password": "789",
      "id": "2kic1w8akkzin30nf"
    },
    {
      "password": "78563",
      "id": "2kic1w1mkkzinejbx"
    },
    {
      "password": "123",
      "id": "2kic1wc8skzio32x3"
    },
    {
      "password": "789",
      "id": "2kic1w73wkzio650p"
    },
    {
      "password": "147",
      "id": "99hxk6b4kzjl8ipj"
    },
    {
      "password": "123",
      "id": "99hxk5awkzjlaj6v"
    },
    {
      "password": "753",
      "id": "99hxkc7okzjlnl3g"
    },
    {
      "password": "789",
      "id": "99hxk4hkkzjm6g3o"
    },
    {
      "password": "123",
      "id": "99hxkaekkzjmdlh5"
    },
    {
      "password": "123",
      "id": "99hxk2bgkzjme4vv"
    },
    {
      "password": "1",
      "id": "99hxkaf4kzjmnn18"
    },
    {
      "password": "123",
      "id": "99hxk8jwkzjtpsr4"
    },
    {
      "password": "1459",
      "id": "99hxkbf8kzjujc79"
    },
    {
      "password": "132",
      "id": "2kic1wcqskzjvtuha"
    },
    {
      "password": "123",
      "id": "2kic1w9k8kzjwx7k6"
    },
    {
      "password": "123",
      "id": "2kic1w66kkzk16gel"
    },
    {
      "password": "123",
      "id": "2kic1w9e8kzk177kj"
    },
    {
      "password": "123",
      "id": "99hxka3wkzk2am8e"
    },
    {
      "password": "123",
      "id": "99hxkcqskzld5it6"
    },
    {
      "password": "123",
      "id": "99hxkcm0kzleaplr"
    },
    {
      "password": "132",
      "id": "99hxk45okzlefteg"
    },
    {
      "password": "123",
      "id": "99hxk5y4kzlekc5r"
    },
    {
      "password": "12",
      "id": "99hxka3ckzleqqu9"
    },
    {
      "password": "123",
      "id": "99hxk9g8kzlev34h"
    },
    {
      "password": "123",
      "id": "2kic1wan4kzmw3iti"
    },
    {
      "password": "123",
      "id": "99hxk3c0kznpyvfc"
    },
    {
      "password": "123",
      "id": "99hxk9zwkzo8gg2m"
    },
    {
      "password": "123",
      "id": "99hxkcy4kzocr9n8"
    },
    {
      "password": "132",
      "id": "99hxkc8okzocywq0"
    },
    {
      "name": "Дмитрий",
      "email": "dmitry@mail.ru",
      "password": "12345",
      "id": "99hxk64ckzofkkf1"
    },
    {
      "name": "Кот",
      "email": "cat@mail.ru",
      "password": "123",
      "id": "g2pchabgkztsqfm2"
    },
    {
      "name": "Аркадий",
      "email": "arkadiq@mail.ru",
      "password": "123",
      "id": "99hxk25kkzvkns0l"
    },
    {
      "name": "Дмитрий",
      "email": "as@mail.ru",
      "password": "123",
      "id": "99hxk9zgkzwzvobq"
    },
    {
      "name": "Дмитрий",
      "email": "122@122",
      "password": "122",
      "id": "99hxk8r4kzx002h6"
    },
    {
      "name": "Дмитрий",
      "email": "dima@mail.ru",
      "password": "12345",
      "id": "99hxk4cgl02pqev4"
    }
  ],
  "accounts": [
    {
      "name": "Банк",
      "user_id": "1",
      "id": "1"
    },
    {
      "name": "Магазин",
      "user_id": "1",
      "id": "2"
    },
    {
      "name": "Бизнес",
      "user_id": "1",
      "id": "3"
    },
    {
      "user_id": "99hxk58wkzhc1zoa",
      "id": "99hxk6xgkzhc9p0x"
    },
    {
      "user_id": "2kic1wc2okzibi0z1",
      "id": "99hxk7f4kzibi5tm"
    },
    {
      "user_id": "99hxkal4kzibvxad",
      "id": "99hxk2rckzibw4wj"
    },
    {
      "user_id": "2kic1wan4kzidyahb",
      "id": "2kic1w9ukkzie3izf"
    },
    {
      "user_id": "2kic1wan4kzidyahb",
      "id": "2kic1w9p8kzie4anr"
    },
    {
      "user_id": "2kic1wan4kzidyahb",
      "id": "2kic1w1eckzie55uh"
    },
    {
      "user_id": "2kic1wan4kzidyahb",
      "id": "2kic1w11ckzie7iwc"
    },
    {
      "user_id": "2kic1wan4kzidyahb",
      "id": "2kic1wcf8kzigp3ul"
    },
    {
      "user_id": "2kic1wan4kzidyahb",
      "id": "2kic1w64gkzih70cb"
    },
    {
      "user_id": "2kic1w7ykkzih790w",
      "id": "2kic1w7kckzih7daw"
    },
    {
      "user_id": "2kic1w7ykkzih790w",
      "id": "2kic1w73gkzihatx9"
    },
    {
      "user_id": "99hxk818kzijtfv5",
      "id": "99hxk65wkzijtnoe"
    },
    {
      "user_id": "99hxk6ygkzijwt85",
      "id": "99hxk57wkzik7mf6"
    },
    {
      "user_id": "99hxk6ygkzijwt85",
      "id": "99hxk4y0kzikp0qx"
    },
    {
      "user_id": "99hxk6ygkzijwt85",
      "id": "99hxk8e0kziks4u0"
    },
    {
      "user_id": "99hxk6ygkzijwt85",
      "id": "99hxk4b0kziktcr9"
    },
    {
      "user_id": "99hxk6ygkzijwt85",
      "id": "99hxk6p8kzikv4we"
    },
    {
      "user_id": "99hxk6ygkzijwt85",
      "id": "99hxk1ockzikx6cp"
    },
    {
      "user_id": "99hxkbkkkzil15eq",
      "id": "99hxk3f0kzil1dtr"
    },
    {
      "user_id": "99hxkbkkkzil15eq",
      "id": "99hxk6i8kzil37dm"
    },
    {
      "user_id": "99hxkbkkkzil15eq",
      "id": "99hxk1c4kzil7v1t"
    },
    {
      "user_id": "99hxkbkkkzil15eq",
      "id": "99hxk7nkkzil94ux"
    },
    {
      "user_id": "99hxkbkkkzil15eq",
      "id": "99hxk604kzilffa1"
    },
    {
      "user_id": "99hxkbkkkzil15eq",
      "id": "99hxka4gkziljxea"
    },
    {
      "user_id": "99hxkbkkkzil15eq",
      "id": "99hxk9w8kzilntaq"
    },
    {
      "user_id": "99hxkbkkkzil15eq",
      "id": "99hxk8vokzilqtdk"
    },
    {
      "user_id": "99hxk6nskzim19wk",
      "id": "99hxk12ckzim1mxj"
    },
    {
      "user_id": "2kic1w9g0kzim6p2s",
      "id": "2kic1wak0kzimexmr"
    },
    {
      "user_id": "2kic1w9g0kzim6p2s",
      "id": "2kic1wsskzimgeek"
    },
    {
      "user_id": "2kic1wau4kzimlk13",
      "id": "2kic1w32gkzimlp1p"
    },
    {
      "user_id": "2kic1wau4kzimlk13",
      "id": "2kic1w8n8kzimm4f3"
    },
    {
      "user_id": "2kic1w9f4kzimqtrg",
      "id": "2kic1w4lgkzimrpvm"
    },
    {
      "user_id": "2kic1w9f4kzimqtrg",
      "id": "2kic1wayokzimrwvo"
    },
    {
      "user_id": "2kic1w7eokzimukvw",
      "id": "2kic1w7vgkzimusrt"
    },
    {
      "user_id": "2kic1w7eokzimukvw",
      "id": "2kic1w9c8kzimuzo9"
    },
    {
      "user_id": "2kic1w14okzimyput",
      "id": "2kic1w8nskzin0oup"
    },
    {
      "user_id": "2kic1w14okzimyput",
      "id": "2kic1wtskzin17m9"
    },
    {
      "user_id": "2kic1w8akkzin30nf",
      "id": "2kic1w5qskzin3k75"
    },
    {
      "user_id": "2kic1w8akkzin30nf",
      "id": "2kic1wbegkzin3otx"
    },
    {
      "user_id": "2kic1w8akkzin30nf",
      "id": "2kic1w8o4kzin4fe0"
    },
    {
      "user_id": "2kic1w8akkzin30nf",
      "id": "2kic1wao4kzin6g3o"
    },
    {
      "user_id": "2kic1w8akkzin30nf",
      "id": "2kic1w1t0kzina6nv"
    },
    {
      "user_id": "2kic1w1mkkzinejbx",
      "id": "2kic1w5tkkzinenvj"
    },
    {
      "user_id": "2kic1w1mkkzinejbx",
      "id": "2kic1w21gkzinf42i"
    },
    {
      "user_id": "2kic1w1mkkzinejbx",
      "id": "2kic1w474kzinfyrd"
    },
    {
      "user_id": "2kic1w1mkkzinejbx",
      "id": "2kic1wba4kzinklnc"
    },
    {
      "user_id": "2kic1w1mkkzinejbx",
      "id": "2kic1wbcwkzinnafb"
    },
    {
      "user_id": "2kic1wc8skzio32x3",
      "id": "2kic1wbbkkzio36vm"
    },
    {
      "user_id": "2kic1wc8skzio32x3",
      "id": "2kic1w3eskzio4oal"
    },
    {
      "user_id": "2kic1w73wkzio650p",
      "id": "2kic1w72kkzio69nm"
    },
    {
      "user_id": "2kic1w73wkzio650p",
      "id": "2kic1w7v4kzio6fyp"
    },
    {
      "user_id": "2kic1w73wkzio650p",
      "id": "2kic1w55kkzioa9xz"
    },
    {
      "user_id": "2kic1w73wkzio650p",
      "id": "2kic1w5fkkzioai0d"
    },
    {
      "user_id": "99hxk6b4kzjl8ipj",
      "id": "99hxk2t4kzjl8phb"
    },
    {
      "user_id": "99hxk5awkzjlaj6v",
      "id": "99hxk9hwkzjlcvhg"
    },
    {
      "user_id": "99hxk5awkzjlaj6v",
      "id": "99hxk5awkzjld788"
    },
    {
      "user_id": "99hxk5awkzjlaj6v",
      "id": "99hxk9uokzjle2my"
    },
    {
      "user_id": "99hxkc7okzjlnl3g",
      "id": "99hxk190kzjlnr11"
    },
    {
      "user_id": "99hxkc7okzjlnl3g",
      "id": "99hxk4ikkzjly2ox"
    },
    {
      "user_id": "99hxkc7okzjlnl3g",
      "id": "99hxk8z8kzjlzguq"
    },
    {
      "user_id": "99hxkc7okzjlnl3g",
      "id": "99hxk7lskzjlzzia"
    },
    {
      "user_id": "99hxkc7okzjlnl3g",
      "id": "99hxkbs0kzjm3lu2"
    },
    {
      "user_id": "99hxkc7okzjlnl3g",
      "id": "99hxk8vckzjm46i9"
    },
    {
      "user_id": "99hxkc7okzjlnl3g",
      "id": "99hxka3skzjm4f7l"
    },
    {
      "user_id": "99hxkc7okzjlnl3g",
      "id": "99hxkzckzjm5un5"
    },
    {
      "user_id": "99hxk4hkkzjm6g3o",
      "id": "99hxk2fokzjm6kf3"
    },
    {
      "user_id": "99hxk4hkkzjm6g3o",
      "id": "99hxka8gkzjm86y1"
    },
    {
      "user_id": "99hxk4hkkzjm6g3o",
      "id": "99hxkay8kzjm8q2x"
    },
    {
      "user_id": "99hxk4hkkzjm6g3o",
      "id": "99hxkay8kzjm8q34"
    },
    {
      "user_id": "99hxk4hkkzjm6g3o",
      "id": "99hxk56gkzjmb6du"
    },
    {
      "user_id": "99hxk4hkkzjm6g3o",
      "id": "99hxk56gkzjmb6e4"
    },
    {
      "user_id": "99hxk2bgkzjme4vv",
      "id": "99hxk6ogkzjmer8a"
    },
    {
      "user_id": "99hxk2bgkzjme4vv",
      "id": "99hxk32kkzjmf9yy"
    },
    {
      "user_id": "99hxk2bgkzjme4vv",
      "id": "99hxk11wkzjmfx02"
    },
    {
      "user_id": "99hxk2bgkzjme4vv",
      "id": "99hxk7pokzjmkbk1"
    },
    {
      "user_id": "99hxk2bgkzjme4vv",
      "id": "99hxk5rokzjmmn3x"
    },
    {
      "user_id": "99hxkaf4kzjmnn18",
      "id": "99hxk1mckzjmo9bl"
    },
    {
      "user_id": "99hxkaf4kzjmnn18",
      "id": "99hxk930kzjmoijv"
    },
    {
      "user_id": "99hxk8jwkzjtpsr4",
      "id": "99hxkxwkzjtsw5f"
    },
    {
      "user_id": "99hxkbf8kzjujc79",
      "id": "99hxk97ckzjult8a"
    },
    {
      "user_id": "2kic1wcqskzjvtuha",
      "id": "2kic1wcqkkzjvv7zy"
    },
    {
      "user_id": "2kic1wcqskzjvtuha",
      "id": "2kic1wdf0kzjw3h90"
    },
    {
      "user_id": "2kic1w9k8kzjwx7k6",
      "id": "2kic1w814kzjwxdj6"
    },
    {
      "user_id": "2kic1w9k8kzjwx7k6",
      "id": "2kic1w3wskzjx60b5"
    },
    {
      "user_id": "2kic1w66kkzk16gel",
      "id": "2kic1wd98kzk16j72"
    },
    {
      "user_id": "2kic1w9e8kzk177kj",
      "id": "2kic1w5vokzk17dim"
    },
    {
      "user_id": "2kic1w9e8kzk177kj",
      "id": "2kic1w11ckzk17mah"
    },
    {
      "user_id": "99hxka3wkzk2am8e",
      "id": "99hxk1fokzk2asxd"
    },
    {
      "user_id": "99hxka3wkzk2am8e",
      "id": "99hxk4mwkzk2wljv"
    },
    {
      "user_id": "99hxka3wkzk2am8e",
      "id": "99hxkciskzk2ywb5"
    },
    {
      "user_id": "99hxkcqskzld5it6",
      "id": "99hxk2ygkzld5tr9"
    },
    {
      "user_id": "99hxkcqskzld5it6",
      "id": "99hxk3fckzldrjhh"
    },
    {
      "user_id": "99hxkcm0kzleaplr",
      "id": "99hxkcwckzleb6kc"
    },
    {
      "user_id": "99hxk45okzlefteg",
      "id": "99hxk9cokzleg8mc"
    },
    {
      "user_id": "99hxka3ckzleqqu9",
      "id": "99hxkbn0kzler6lg"
    },
    {
      "user_id": "99hxk9g8kzlev34h",
      "id": "99hxk81gkzlev7t6"
    },
    {
      "user_id": "2kic1wan4kzmw3iti",
      "id": "2kic1w7g4kzmw94qw"
    },
    {
      "user_id": "99hxk3c0kznpyvfc",
      "id": "99hxk8k0kznq5c2r"
    },
    {
      "user_id": "99hxk9zwkzo8gg2m",
      "id": "99hxkl8kzo8gpck"
    },
    {
      "name": "Сбербанк",
      "user_id": "99hxk64ckzofkkf1",
      "id": "99hxk7uskzogejgi"
    },
    {
      "name": "Wisskass",
      "user_id": "g2pchabgkztsqfm2",
      "id": "g2pch4mskztsqu37"
    },
    {
      "name": "Вебмани",
      "user_id": "99hxk64ckzofkkf1",
      "id": "99hxkc4sl02puy93"
    }
  ],
  "transactions": [
    {
      "account_id": "1",
      "created_at": "2019-09-15 10:24:02",
      "id": "1",
      "name": "Кредит",
      "sum": 5000,
      "type": "expense",
      "user_id": "1"
    },
    {
      "account_id": "1",
      "created_at": "2019-09-17 15:53:02",
      "id": "2",
      "name": "Баланс на дебетовке",
      "sum": 3200,
      "type": "income",
      "user_id": "1"
    },
    {
      "account_id": "1",
      "created_at": "2019-09-19 20:12:02",
      "id": "3",
      "name": "Копилка",
      "sum": 1500,
      "type": "income",
      "user_id": "1"
    },
    {
      "account_id": "2",
      "created_at": "2019-09-26 16:23:02",
      "id": "4",
      "name": "Молочные продукты",
      "sum": 100,
      "type": "income",
      "user_id": "1"
    },
    {
      "account_id": "2",
      "created_at": "2019-09-25 15:03:02",
      "id": "5",
      "name": "Фрукты",
      "sum": 250,
      "type": "income",
      "user_id": "1"
    },
    {
      "account_id": "2",
      "created_at": "2019-09-25 15:03:02",
      "id": "17",
      "name": "Овощи",
      "sum": 300,
      "type": "income",
      "user_id": "1"
    },
    {
      "account_id": "2",
      "created_at": "2019-09-26 14:47:02",
      "id": "6",
      "name": "Мясо",
      "sum": 600,
      "type": "income",
      "user_id": "1"
    },
    {
      "account_id": "2",
      "created_at": "2019-09-27 13:27:02",
      "id": "7",
      "name": "Долг в банк",
      "sum": 5000,
      "type": "expense",
      "user_id": "1"
    },
    {
      "account_id": "3",
      "created_at": "2017-10-15 13:27:02",
      "id": "9",
      "name": "На банду",
      "sum": 15000,
      "type": "expense",
      "user_id": "1"
    },
    {
      "account_id": "3",
      "created_at": "2017-09-17 13:27:02",
      "id": "10",
      "name": "На стволы",
      "sum": 6000,
      "type": "expense",
      "user_id": "1"
    },
    {
      "account_id": "3",
      "created_at": "2017-12-27 13:27:02",
      "id": "11",
      "name": "Прибыль с банка",
      "sum": 1500000,
      "type": "income",
      "user_id": "1"
    },
    {
      "account_id": "3",
      "created_at": "2018-01-15 13:27:02",
      "id": "12",
      "name": "Прибыль с магазина",
      "sum": 300000,
      "type": "income",
      "user_id": "1"
    },
    {
      "account_id": "3",
      "created_at": "2018-01-15 13:27:02",
      "id": "13",
      "name": "Подарок сизого",
      "sum": 20000,
      "type": "income",
      "user_id": "1"
    },
    {
      "account_id": "3",
      "created_at": "2017-09-15 13:27:02",
      "id": "14",
      "name": "На охрану",
      "sum": 60000,
      "type": "expense",
      "user_id": "1"
    },
    {
      "account_id": "3",
      "created_at": "2017-10-15 13:27:02",
      "id": "15",
      "name": "На бумер",
      "sum": 300000,
      "type": "expense",
      "user_id": "1"
    },
    {
      "id": "g2pchaagkztplig2",
      "type": "income",
      "name": "Зарплата",
      "sum": 120000,
      "account_id": "99hxk7uskzogejgi",
      "user_id": "99hxk64ckzofkkf1",
      "created_at": "2022-02-19T10:39:36.865Z"
    },
    {
      "id": "g2pch6d4kztsso0n",
      "type": "income",
      "name": "Зарплата",
      "sum": 15000,
      "account_id": "g2pch4mskztsqu37",
      "user_id": "g2pchabgkztsqfm2",
      "created_at": "2022-02-19T12:09:09.526Z"
    },
    {
      "id": "99hxk8vsl02pskw8",
      "type": "expense",
      "name": "Шуба",
      "sum": 100000,
      "account_id": "99hxk7uskzogejgi",
      "user_id": "99hxk64ckzofkkf1",
      "created_at": "2022-02-25T17:55:02.215Z"
    },
    {
      "id": "99hxk2i8l02pv8kx",
      "type": "income",
      "name": "Пополнение",
      "sum": 1000,
      "account_id": "99hxkc4sl02puy93",
      "user_id": "99hxk64ckzofkkf1",
      "created_at": "2022-02-25T17:57:06.224Z"
    }
  ]
}